{
  "name": "Courier",
  "fields": [
    {
      "fieldName": "working",
      "fieldType": "Boolean",
      "fieldValidateRules": ["required"]
    },
    {
      "fieldName": "imageProfil",
      "fieldType": "byte[]",
      "fieldTypeBlobContent": "image"
    },
    {
      "fieldName": "mobilePhone",
      "fieldType": "String",
      "fieldValidateRules": ["required"]
    }
  ],
  "relationships": [
    {
      "relationshipType": "one-to-one",
      "otherEntityName": "user",
      "otherEntityRelationshipName": "courier",
      "relationshipName": "user",
      "otherEntityField": "login",
      "ownerSide": true
    },
    {
      "relationshipType": "many-to-one",
      "otherEntityName": "cooperative",
      "otherEntityRelationshipName": "courier",
      "relationshipName": "cooperative",
      "otherEntityField": "cooperativeName"
    }
  ],
  "entityTableName": "courier",
  "dto": "mapstruct",
  "pagination": "no",
  "service": "serviceClass",
  "jpaMetamodelFiltering": false,
  "fluentMethods": true,
  "readOnly": false,
  "embedded": false,
  "applications": "*",
  "changelogDate": "20210411134838"
}
